README
ez_setup.py
setup.cfg
setup.py
sipie.py
Sipie/Config.py
Sipie/Factory.py
Sipie/Player.py
Sipie/Popup.py
Sipie/StreamHandler.py
Sipie/__init__.py
Sipie/cliPlayer.py
Sipie/gtkPlayer.py
Sipie/wxPlayer.py
Sipie.egg-info/PKG-INFO
Sipie.egg-info/SOURCES.txt
Sipie.egg-info/dependency_links.txt
Sipie.egg-info/entry_points.txt
Sipie.egg-info/requires.txt
Sipie.egg-info/top_level.txt
Sipie.egg-info/zip-safe
Sipie/data/gtkSipie.glade
Sipie/data/sipie.png
docs/cliExample.py
docs/example.py
docs/examplePopups.py
