Metadata-Version: 1.0
Name: Sipie
Version: 0.1196144357
Summary: Library and Player for Sirius Online Streaming
Home-page: http://sipie.sourceforge.net/
Author: Eli Criffield
Author-email: python@zendo.net
License: http://www.gnu.org/licenses/gpl.txt
Platform: any
Classifier: Development Status :: 4 - Beta
Classifier: Environment :: Console
Classifier: Environment :: X11 Applications :: GTK
Classifier: Intended Audience :: End Users/Desktop
Classifier: Intended Audience :: Developers
Classifier: License :: OSI Approved :: GNU General Public License (GPL)
Classifier: Operating System :: OS Independent
Classifier: Programming Language :: Python
Classifier: Topic :: Multimedia :: Sound/Audio :: Players
Classifier: Topic :: Software Development :: Libraries :: Python Modules
